.codecov.yml
.gitignore
.pre-commit-config.yaml
.readthedocs.yaml
.snyk
CHANGELOG.md
DEVELOPMENT.rst
LICENSE
README.rst
dockerfile
publish.sh
setup.py
.circleci/config.yml
.github/CODEOWNERS
.github/PULL_REQUEST_TEMPLATE.md
.github/stale.yml
.github/ISSUE_TEMPLATE/config.yml
.github/ISSUE_TEMPLATE/feature_request.md
.github/ISSUE_TEMPLATE/report_a_bug.md
authok/__init__.py
authok/v3/__init__.py
authok/v3/exceptions.py
authok/v3/authentication/__init__.py
authok/v3/authentication/authorize_client.py
authok/v3/authentication/base.py
authok/v3/authentication/database.py
authok/v3/authentication/delegated.py
authok/v3/authentication/enterprise.py
authok/v3/authentication/get_token.py
authok/v3/authentication/logout.py
authok/v3/authentication/passwordless.py
authok/v3/authentication/revoke_token.py
authok/v3/authentication/social.py
authok/v3/authentication/token_verifier.py
authok/v3/authentication/users.py
authok/v3/management/__init__.py
authok/v3/management/actions.py
authok/v3/management/attack_protection.py
authok/v3/management/auth0.py
authok/v3/management/blacklists.py
authok/v3/management/client_grants.py
authok/v3/management/clients.py
authok/v3/management/connections.py
authok/v3/management/custom_domains.py
authok/v3/management/device_credentials.py
authok/v3/management/email_templates.py
authok/v3/management/emails.py
authok/v3/management/grants.py
authok/v3/management/guardian.py
authok/v3/management/hooks.py
authok/v3/management/jobs.py
authok/v3/management/log_streams.py
authok/v3/management/logs.py
authok/v3/management/organizations.py
authok/v3/management/prompts.py
authok/v3/management/resource_servers.py
authok/v3/management/rest.py
authok/v3/management/roles.py
authok/v3/management/rules.py
authok/v3/management/rules_configs.py
authok/v3/management/stats.py
authok/v3/management/tenants.py
authok/v3/management/tickets.py
authok/v3/management/user_blocks.py
authok/v3/management/users.py
authok/v3/management/users_by_email.py
authok_python.egg-info/PKG-INFO
authok_python.egg-info/SOURCES.txt
authok_python.egg-info/dependency_links.txt
authok_python.egg-info/requires.txt
authok_python.egg-info/top_level.txt
